pyoxigraph_pydantic/__init__.py
pyoxigraph_pydantic-0.1.0.dist-info/LICENSE
pyoxigraph_pydantic-0.1.0.dist-info/METADATA
pyoxigraph_pydantic-0.1.0.dist-info/WHEEL
pyoxigraph_pydantic-0.1.0.dist-info/RECORD
